pynecone_admin/__init__.py
pynecone_admin/auth.py
pynecone_admin/auth_models.py
pynecone_admin/crud.py
pynecone_admin/persistent_token.py
pynecone_admin/utils.py
pynecone_admin/components/__init__.py
pynecone_admin/components/select.py
pynecone_admin-0.1a0.dist-info/LICENSE
pynecone_admin-0.1a0.dist-info/METADATA
pynecone_admin-0.1a0.dist-info/WHEEL
pynecone_admin-0.1a0.dist-info/top_level.txt
pynecone_admin-0.1a0.dist-info/RECORD
